materials_spum_multi/__init__.py
materials_spum_multi/annotation.py
materials_spum_multi/assets.py
materials_spum_multi/crf.py
materials_spum_multi/database.py
materials_spum_multi/match.py
materials_spum_multi/primitives.py
materials_spum_multi/sample.py
materials_spum_multi/train.py
materials_spum_multi/util.py
materials_spum_multi/api/models.py
materials_spum_multi-0.1.4.dist-info/METADATA
materials_spum_multi-0.1.4.dist-info/WHEEL
materials_spum_multi-0.1.4.dist-info/RECORD
